cred/__init__.py
cred/borrowing.py
cred/businessdays.py
cred/interest_rate.py
cred/period.py
cred/prepayment.py
cred-0.2.3.dist-info/LICENSE
cred-0.2.3.dist-info/METADATA
cred-0.2.3.dist-info/WHEEL
cred-0.2.3.dist-info/top_level.txt
cred-0.2.3.dist-info/RECORD
