Metadata-Version: 2.1
Name: cred
Version: 0.2.3
Summary: Model commercial real estate debt
Home-page: https://github.com/jordanhitchcock/cred'
License: MIT
Keywords: real estate,debt,mortgage,finance
Platform: UNKNOWN
Classifier: License :: OSI Approved :: MIT License
Classifier: Programming Language :: Python :: 3
Classifier: Topic :: Office/Business :: Financial
Classifier: Topic :: Office/Business :: Financial :: Investment
Classifier: Intended Audience :: Financial and Insurance Industry
Classifier: Development Status :: 4 - Beta
Requires-Python: >=3.6
License-File: LICENSE
Requires-Dist: pandas (>=0.25.2)
Requires-Dist: python-dateutil (>=2.8.0)
Requires-Dist: holidaycal
